pyclouds/.f2py_f2cmap
pyclouds/.gitignore
pyclouds/Makefile
pyclouds/__init__.py
pyclouds/_version.py
pyclouds/dev/fortran-microphysics.py
pyclouds/dev/fortran_isometric-isobaric_integration.py
pyclouds/dev/full-eqns.py
pyclouds/dev/microphysics.py
pyclouds/dev/old_kessler_fortran.py
pyclouds/dev/plots/.gitignore
pyclouds/dev/plots/old_kessler_vs_finite_condevap_rate.py
pyclouds/dev/pseudotime-integration-dry.py
pyclouds/dev/pseudotime-integration.py
pyclouds/integration/__init__.py
pyclouds/integration/methods.py
pyclouds/integration/parcel/__init__.py
pyclouds/integration/parcel/handler.py
pyclouds/integration/parcel/stopping.py
pyclouds/integration/parcel_initiation.py
pyclouds/models/__init__.py
pyclouds/models/ccfm/__init__.py
pyclouds/models/ccfm/ccfmfortran/Makefile
pyclouds/models/ccfm/ccfmfortran/__init__.py
pyclouds/models/ccfm/ccfmfortran/fortranlib.so
pyclouds/models/ccfm/ccfmfortran/microphysics.py
pyclouds/models/ccfm/ccfmfortran/mo_ccfm_cloudbase.f90
pyclouds/models/ccfm/ccfmfortran/mo_ccfm_parameter.f90
pyclouds/models/ccfm/ccfmpython/__init__.py
pyclouds/models/ccfm/ccfmpython/microphysics.py
pyclouds/models/ccfm/version0/Makefile
pyclouds/models/ccfm/version0/__init__.py
pyclouds/models/ccfm/version0/ccfm.f90
pyclouds/models/ccfm/version0/ccfm_cloud_model.f90
pyclouds/models/ccfm/version0/ccfm_microphysics.f90
pyclouds/models/ccfm/version0/fortranlib.so
pyclouds/models/ccfm/version0/mo_ccfm_parameter.f90
pyclouds/models/microphysics.py
pyclouds/models/parcel.py
pyclouds/plot/.gitignore
pyclouds/plot/__init__.py
pyclouds/plot/parameterisations.py
pyclouds/plot/parcel.py
pyclouds/plot/pv_sat.py
pyclouds/reference/__init__.py
pyclouds/reference/atmos/.gitignore
pyclouds/reference/atmos/__init__.py
pyclouds/reference/atmos/atmospheres.py
pyclouds/reference/atmos/gas_properties.py
pyclouds/reference/atmos/lapse_rate_study.py
pyclouds/reference/atmos/plots/isentropic_atmosphere.py
pyclouds/reference/atmos/saturation_calculation.py
pyclouds-0.2.1.dist-info/WHEEL
pyclouds-0.2.1.dist-info/METADATA
pyclouds-0.2.1.dist-info/RECORD
